[
    {
        "id_group": 24,
        "disband_year": "2019"
    },
    {
        "id_group": 37,
        "disband_year": "2021"
    },
    {
        "id_group": 45,
        "disband_year": "2021"
    },
    {
        "id_group": 80,
        "disband_year": "2023"
    },
    {
        "id_group": 81,
        "disband_year": "2023"
    },
    {
        "id_group": 82,
        "disband_year": "2023"
    },
    {
        "id_group": 83,
        "disband_year": "2023"
    },
    {
        "id_group": 84,
        "disband_year": "2023"
    },
    {
        "id_group": 85,
        "disband_year": "2024"
    },
    {
        "id_group": 86,
        "disband_year": "2023"
    },
    {
        "id_group": 89,
        "disband_year": "2024"
    },
    {
        "id_group": 90,
        "disband_year": "2024"
    },
    {
        "id_group": 92,
        "disband_year": "2023"
    },
    {
        "id_group": 93,
        "disband_year": "2024"
    },
    {
        "id_group": 96,
        "disband_year": "2023"
    },
    {
        "id_group": 97,
        "disband_year": "2022"
    },
    {
        "id_group": 98,
        "disband_year": "2025"
    }
]